phantom_tensors/__init__.py
phantom_tensors/_version.py
phantom_tensors/alphabet.py
phantom_tensors/array.py
phantom_tensors/errors.py
phantom_tensors/meta.py
phantom_tensors/numpy.py
phantom_tensors/parse.py
phantom_tensors/py.typed
phantom_tensors/torch.py
phantom_tensors/words.py
phantom_tensors/_internals/__init__.py
phantom_tensors/_internals/dim_binding.py
phantom_tensors/_internals/parse.py
phantom_tensors/_internals/utils.py
phantom_tensors-0.3.0.dist-info/LICENSE.txt
phantom_tensors-0.3.0.dist-info/METADATA
phantom_tensors-0.3.0.dist-info/WHEEL
phantom_tensors-0.3.0.dist-info/top_level.txt
phantom_tensors-0.3.0.dist-info/RECORD
