Metadata-Version: 2.1
Name: phantom_tensors
Version: 0.3.0
Summary: Tensor-like types – with variadic shapes – that support both static and runtime type checking, and convenient parsing.
Author-email: Ryan Soklaski <rsoklaski@gmail.com>, Justin Goodwin <jgoodwin@ll.mit.edu>
Maintainer-email: Justin Goodwin <jgoodwin@ll.mit.edu>
License: MIT
Project-URL: Homepage, https://github.com/rsokl/phantom-tensors/
Project-URL: Bug Reports, https://github.com/rsokl/phantom-tensors/issues
Project-URL: Source, https://github.com/rsokl/phantom-tensors
Keywords: machine learning,research,configuration,scalable,reproducible,yaml,Hydra,dataclass
Classifier: Development Status :: 4 - Beta
Classifier: License :: OSI Approved :: MIT License
Classifier: Operating System :: OS Independent
Classifier: Intended Audience :: Science/Research
Classifier: Programming Language :: Python :: 3.8
Classifier: Programming Language :: Python :: 3.9
Classifier: Programming Language :: Python :: 3.10
Classifier: Programming Language :: Python :: 3.11
Classifier: Programming Language :: Python :: 3.12
Classifier: Topic :: Scientific/Engineering
Classifier: Programming Language :: Python :: 3 :: Only
Requires-Python: >=3.8
License-File: LICENSE.txt
Requires-Dist: typing-extensions >=4.1.0
Provides-Extra: test
Requires-Dist: beartype >=0.10.4 ; extra == 'test'
Requires-Dist: pytest >=3.8 ; extra == 'test'
Requires-Dist: hypothesis >=6.28.0 ; extra == 'test'
